DeGourou/DeGourou.py
DeGourou/decrypt/__init__.py
DeGourou/decrypt/decodeEPUB.py
DeGourou/decrypt/decodePDF.py
DeGourou/decrypt/params.py
DeGourou/decrypt/zeroedzipinfo.py
DeGourou/setup/__init__.py
DeGourou/setup/customRSA.py
DeGourou/setup/data.py
DeGourou/setup/fulfill.py
DeGourou/setup/ia.py
DeGourou/setup/libadobe.py
DeGourou/setup/libadobeAccount.py
DeGourou/setup/libadobeFulfill.py
DeGourou/setup/libpdf.py
DeGourou/setup/loginAccount.py
DeGourou/setup/params.py
DeGourou-1.3.9.dist-info/LICENSE
DeGourou-1.3.9.dist-info/METADATA
DeGourou-1.3.9.dist-info/WHEEL
DeGourou-1.3.9.dist-info/entry_points.txt
DeGourou-1.3.9.dist-info/top_level.txt
DeGourou-1.3.9.dist-info/RECORD
