Metadata-Version: 2.1
Name: DeGourou
Version: 1.3.9
Summary: Automate the process of getting decrypted ebook from InternetArchive without the need for Adobe Digital Editions and Calibre.
Home-page: https://gitea.com/bipinkrish/DeGourou
Author: Bipin krishna
License: GPL3
Classifier: Development Status :: 5 - Production/Stable
Classifier: Intended Audience :: Science/Research
Classifier: License :: OSI Approved :: GNU General Public License v3 (GPLv3)
Classifier: Operating System :: MacOS
Classifier: Operating System :: Microsoft :: Windows
Classifier: Operating System :: POSIX :: Linux
Classifier: Programming Language :: Python :: 3.6
Classifier: Programming Language :: Python :: 3.7
Classifier: Programming Language :: Python :: 3.8
Classifier: Programming Language :: Python :: 3.9
License-File: LICENSE
Requires-Dist: pycryptodomex >=3.17
Requires-Dist: cryptography >=41.0.1
Requires-Dist: lxml >=4.9.2
Requires-Dist: requests >=2.31.0
Requires-Dist: charset-normalizer >=3.1.0
